{
    "version": "1.2.3",
    "description": "A minimal writing application",
    "homepage": "https://gitee.com/knowshub/only-write",
    "license": "MIT",
    "architecture": {
        "64bit": {
            "url": "https://gitee.com/knowshub/only-write/releases/download/Windows-1.2.3/Windows-1.2.3.rar",
            "hash": "sha256:2c84ab9c1d14331c9c13fb0474300e603140dcf135cc69053162be84f5cf34b5"
        }
    },
    "installer": {
        "script":[
            "$subdir = Join-Path -Path \"$dir\" -ChildPath \"Windows-1.2.3\"",
            "if (Test-Path \"$subdir\") { Move-Item -Path \"$subdir\\*\" -Destination \"$dir\" -Force; Remove-Item -Path \"$subdir\" -Recurse -Force }"
        ]
    },
    "bin": "onlywriter.exe",
    "shortcuts": [
        [
            "onlywriter.exe",
            "onlywrite"
        ]
    ],
    "checkver": {
        "url": "https://gitee.com/knowshub/only-write",
        "regex": "releases/tag/Windows-([\\d.]+)"
    },
    "autoupdate": {
        "architecture": {
            "64bit": {
                "url": "https://gitee.com/knowshub/only-write/releases/download/Windows-$version/Windows-$version.rar",
                "hash": {
                    "url": "https://gitee.com/knowshub/only-write/releases/download/Windows-$version/Windows-$version.rar",
                    "regex": "sha256:([a-f0-9]{64})"
                }
            }
        }
    }
}
